benchmarks/__init__.py
benchmarks/benchmark_episodes.py
benchmarks/benchmark_utils.py
benchmarks/flatland_performance_profiling.ipynb
benchmarks/performance_a_star_motion_check.png
benchmarks/performance_a_star_motion_check_new.png
benchmarks/performance_lru.png
benchmarks/performance_lru_new.png
benchmarks/performance_overall.png
benchmarks/performance_overall_new.png
benchmarks/profile_all_examples.py
benchmarks/run_all_examples.py
env_data/__init__.py
env_data/railway/__init__.py
env_data/railway/basic_elements_test.pkl
env_data/railway/complex_scene.pkl
env_data/railway/complex_scene_2.pkl
env_data/railway/example_flatland_000.pkl
env_data/railway/example_flatland_001.pkl
env_data/railway/example_network_000.pkl
env_data/railway/example_network_001.pkl
env_data/railway/example_network_002.pkl
env_data/railway/example_network_003.pkl
env_data/tests/Level_distance_map_shortest_path.mpk
env_data/tests/Test_2_Level_0.pkl
env_data/tests/Test_9_Level_1.pkl
env_data/tests/__init__.py
env_data/tests/test1.npy
env_data/tests/test_001.pkl
env_data/tests/test_002.mpk
env_data/tests/test_env_loop.pkl
env_data/tests/service_test/metadata.csv
env_data/tests/service_test/Test_0/Level_0.pkl
env_data/tests/service_test/Test_0/Level_1.pkl
env_data/tests/service_test/Test_1/Level_0.pkl
env_data/tests/service_test/Test_1/Level_1.pkl
episodes/.gitignore
examples/__init__.py
examples/custom_observation_example_01_SimpleObs.py
examples/custom_observation_example_02_SingleAgentNavigationObs.py
examples/custom_observation_example_03_ObservePredictions.py
examples/custom_railmap_example.py
examples/flatland_3_0_example.py
examples/flatland_performance_profiling.py
examples/interactive_ai.py
examples/introduction_flatland_3.py
examples/sample_10_10_rail.npy
examples/training_example.py
examples/misc/generate_video/video_generation.md
flatland/__init__.py
flatland/cli.py
flatland/callbacks/__init__.py
flatland/callbacks/callbacks.py
flatland/callbacks/generate_movie_callbacks.py
flatland_rl-4.2.3.dist-info/licenses/AUTHORS.md
flatland_rl-4.2.3.dist-info/licenses/LICENSE
flatland_rl-4.2.3.dist-info/METADATA
flatland_rl-4.2.3.dist-info/WHEEL
flatland_rl-4.2.3.dist-info/entry_points.txt
flatland_rl-4.2.3.dist-info/top_level.txt
flatland_rl-4.2.3.dist-info/RECORD
