Metadata-Version: 2.4
Name: flatland-rl
Version: 4.2.3
Summary: Multi Agent Reinforcement Learning on Trains
Author-email: Flatland Association <contact@flatland-association.org>
License: MIT License
Project-URL: Homepage, https://www.flatland-association.org
Project-URL: Github Repository, https://github.com/flatland-association/flatland-rl
Project-URL: Issue Tracker, https://github.com/flatland-association/flatland-rl/issues
Keywords: flatland
Classifier: Development Status :: 4 - Beta
Classifier: Intended Audience :: Developers
Classifier: Natural Language :: English
Classifier: Programming Language :: Python :: 3.10
Classifier: Programming Language :: Python :: 3.11
Classifier: Programming Language :: Python :: 3.12
Classifier: Programming Language :: Python :: 3.13
Requires-Python: >=3.10
License-File: LICENSE
License-File: AUTHORS.md
Requires-Dist: attrs
Requires-Dist: boto3
Requires-Dist: click
Requires-Dist: crowdai_api
Requires-Dist: fastenum
Requires-Dist: importlib_resources
Requires-Dist: ipycanvas
Requires-Dist: ipyevents
Requires-Dist: ipython<9.0.0
Requires-Dist: ipywidgets
Requires-Dist: matplotlib
Requires-Dist: msgpack_numpy
Requires-Dist: msgpack
Requires-Dist: networkx<3.5
Requires-Dist: numpy<2
Requires-Dist: pandas
Requires-Dist: Pillow
Requires-Dist: pyglet
Requires-Dist: pydantic
Requires-Dist: python-dateutil
Requires-Dist: PyYAML
Requires-Dist: requests
Requires-Dist: recordtype
Requires-Dist: redis
Requires-Dist: urllib3
Requires-Dist: typing_extensions
Requires-Dist: tqdm
Requires-Dist: svgutils
Requires-Dist: timeout_decorator
Requires-Dist: versions==1.6.1
Requires-Dist: contourpy<=1.3.2
Provides-Extra: dev
Requires-Dist: coverage; extra == "dev"
Requires-Dist: opencv-python; extra == "dev"
Requires-Dist: deptry; extra == "dev"
Requires-Dist: folium; extra == "dev"
Requires-Dist: flake8; extra == "dev"
Requires-Dist: flake8-eradicate; extra == "dev"
Requires-Dist: ipyplot; extra == "dev"
Requires-Dist: ipycytoscape; extra == "dev"
Requires-Dist: jupyter; extra == "dev"
Requires-Dist: nbmake; extra == "dev"
Requires-Dist: pip-tools; extra == "dev"
Requires-Dist: pytest; extra == "dev"
Requires-Dist: pytest-retry; extra == "dev"
Requires-Dist: seaborn; extra == "dev"
Requires-Dist: snakeviz; extra == "dev"
Requires-Dist: testcontainers; extra == "dev"
Requires-Dist: tox; extra == "dev"
Provides-Extra: ml
Requires-Dist: dm-tree<0.1.9; extra == "ml"
Requires-Dist: pettingzoo; extra == "ml"
Requires-Dist: ray[default,rllib]; extra == "ml"
Requires-Dist: stable_baselines3; extra == "ml"
Requires-Dist: supersuit<3.10.0; extra == "ml"
Requires-Dist: scipy<1.16.0; extra == "ml"
Requires-Dist: torch; extra == "ml"
Requires-Dist: wandb; extra == "ml"
Dynamic: license-file
